{
  "main": {
    "id": "8fbdcd83e85f2345",
    "type": "split",
    "children": [
      {
        "id": "0a7209098daa17b5",
        "type": "tabs",
        "children": [
          {
            "id": "0345561f85e900ae",
            "type": "leaf",
            "state": {
              "type": "canvas",
              "state": {
                "file": "documentation/CharactersDesignCanvas.canvas",
                "viewState": {
                  "x": 95.47115739115172,
                  "y": -205.36193069972353,
                  "zoom": -0.3998623524040277
                }
              }
            }
          }
        ]
      }
    ],
    "direction": "vertical"
  },
  "left": {
    "id": "e5d0eeb754054749",
    "type": "split",
    "children": [
      {
        "id": "b0b4a21d8c044826",
        "type": "tabs",
        "children": [
          {
            "id": "427629d110f977ef",
            "type": "leaf",
            "state": {
              "type": "file-explorer",
              "state": {
                "sortOrder": "alphabetical"
              }
            }
          },
          {
            "id": "5c4a13912830c02b",
            "type": "leaf",
            "state": {
              "type": "search",
              "state": {
                "query": "",
                "matchingCase": false,
                "explainSearch": false,
                "collapseAll": false,
                "extraContext": false,
                "sortOrder": "alphabetical"
              }
            }
          },
          {
            "id": "c5d542f45647ded6",
            "type": "leaf",
            "state": {
              "type": "starred",
              "state": {}
            }
          }
        ]
      }
    ],
    "direction": "horizontal",
    "width": 300
  },
  "right": {
    "id": "52f11e61c2926dfc",
    "type": "split",
    "children": [
      {
        "id": "b08d87776e5a21f9",
        "type": "tabs",
        "children": [
          {
            "id": "8aaa226336270bf4",
            "type": "leaf",
            "state": {
              "type": "backlink",
              "state": {
                "file": "documentation/CharactersDesignCanvas.canvas",
                "collapseAll": false,
                "extraContext": false,
                "sortOrder": "alphabetical",
                "showSearch": false,
                "searchQuery": "",
                "backlinkCollapsed": false,
                "unlinkedCollapsed": true
              }
            }
          },
          {
            "id": "8bdf1e76547b2276",
            "type": "leaf",
            "state": {
              "type": "outgoing-link",
              "state": {
                "file": "documentation/CharactersDesignCanvas.canvas",
                "linksCollapsed": false,
                "unlinkedCollapsed": true
              }
            }
          },
          {
            "id": "13b81b9dab067044",
            "type": "leaf",
            "state": {
              "type": "tag",
              "state": {
                "sortOrder": "frequency",
                "useHierarchy": true
              }
            }
          },
          {
            "id": "9fecd78463532658",
            "type": "leaf",
            "state": {
              "type": "outline",
              "state": {
                "file": "documentation/CharactersDesignCanvas.canvas"
              }
            }
          }
        ]
      }
    ],
    "direction": "horizontal",
    "width": 300,
    "collapsed": true
  },
  "left-ribbon": {
    "hiddenItems": {
      "switcher:Open quick switcher": false,
      "graph:Open graph view": false,
      "canvas:Create new canvas": false,
      "daily-notes:Open today's daily note": false,
      "templates:Insert template": false,
      "command-palette:Open command palette": false
    }
  },
  "active": "0345561f85e900ae",
  "lastOpenFiles": [
    "documentation/images/Pasted image 20230410195441.png",
    "documentation/CharactersDesignCanvas.canvas",
    "documentation/images/FKy5y_wXMAIk5By.jpeg",
    "documentation/images/harena-invite-mamu-reference.jpeg",
    "documentation/images/Hospital-2-640x424.jpg",
    "documentation/images/IMG_5179.jpeg",
    "documentation/images/referece-mamu-original.png",
    "documentation/pages/Characters Design.md",
    "documentation/images/referece-mamu-original.png.import",
    "documentation/images/harena-invite-mamu-reference.jpeg.import",
    "documentation/images/ha-infatil-intenal-facility.jpeg.import",
    "documentation/images/IMG_5179.jpeg.import",
    "documentation/images/Hospital-2-640x424.jpg.import",
    "documentation/images/FKy5y_wXMAIk5By.jpeg.import",
    "documentation/images/ha-infatil-intenal-facility.jpeg",
    "documentation/pages/Game Story Narrative.md",
    "documentation/attachments/HA_OFICIAL_V7.pdf",
    "Narrative.md",
    "documentation/attachments",
    "documentation/images/WhatsApp Image 2023-03-14 at 09.35.28.jpeg",
    "documentation/pages/Scenes Design.md",
    "documentation/images",
    "README.md",
    "Obsidian.md"
  ]
}